acme/__init__.py
acme/challenges.py
acme/client.py
acme/crypto_util.py
acme/errors.py
acme/fields.py
acme/jws.py
acme/messages.py
acme/py.typed
acme/standalone.py
acme/util.py
acme/_internal/__init__.py
acme/_internal/tests/__init__.py
acme/_internal/tests/challenges_test.py
acme/_internal/tests/client_test.py
acme/_internal/tests/conftest.py
acme/_internal/tests/crypto_util_test.py
acme/_internal/tests/errors_test.py
acme/_internal/tests/fields_test.py
acme/_internal/tests/jose_test.py
acme/_internal/tests/jws_test.py
acme/_internal/tests/messages_test.py
acme/_internal/tests/standalone_test.py
acme/_internal/tests/test_util.py
acme/_internal/tests/util_test.py
acme/_internal/tests/testdata/README
acme/_internal/tests/testdata/cert-100sans.pem
acme/_internal/tests/testdata/cert-idnsans.pem
acme/_internal/tests/testdata/cert-ipsans.pem
acme/_internal/tests/testdata/cert-ipv6sans.pem
acme/_internal/tests/testdata/cert-nocn.der
acme/_internal/tests/testdata/cert-san.pem
acme/_internal/tests/testdata/cert.der
acme/_internal/tests/testdata/cert.pem
acme/_internal/tests/testdata/critical-san.pem
acme/_internal/tests/testdata/csr-100sans.pem
acme/_internal/tests/testdata/csr-6sans.pem
acme/_internal/tests/testdata/csr-idnsans.pem
acme/_internal/tests/testdata/csr-ipsans.pem
acme/_internal/tests/testdata/csr-ipv6sans.pem
acme/_internal/tests/testdata/csr-mixed.pem
acme/_internal/tests/testdata/csr-nosans.pem
acme/_internal/tests/testdata/csr-san.pem
acme/_internal/tests/testdata/csr.der
acme/_internal/tests/testdata/csr.pem
acme/_internal/tests/testdata/dsa512_key.pem
acme/_internal/tests/testdata/ec_secp384r1_key.pem
acme/_internal/tests/testdata/rsa1024_cert.pem
acme/_internal/tests/testdata/rsa1024_key.pem
acme/_internal/tests/testdata/rsa2048_cert.pem
acme/_internal/tests/testdata/rsa2048_key.pem
acme/_internal/tests/testdata/rsa256_key.pem
acme/_internal/tests/testdata/rsa4096_cert.pem
acme/_internal/tests/testdata/rsa4096_key.pem
acme-5.0.0.dist-info/licenses/LICENSE.txt
acme-5.0.0.dist-info/METADATA
acme-5.0.0.dist-info/WHEEL
acme-5.0.0.dist-info/top_level.txt
acme-5.0.0.dist-info/RECORD
